{
  "title": "Airbus SE",
  "colors": [
    "00205B"
  ],
  "brandUrl": "http://airbus.com",
  "sourceUrl": "https://brand.airbus.com/en/asset-library/airbus-logo",
  "category": "Aerospace and Defense",
  "description": "Airbus SE is renowned for its presence in the aerospace industry. The brand's colors are deeply associated with its identity, characterized by the striking blue hue '00205B'. This distinctive color palette reflects Airbus's commitment to innovation and excellence in the field. Information about these brand colors is retrieved from the official Airbus brand library, ensuring authenticity and consistency."
}