{
  "title": "Airtel",
  "colors": [
    "D40000",
    "374150",
    "000000",
    "2D2D2D",
    "DCDCDC"
  ],
  "brandUrl": "http://airtel.com",
  "sourceUrl": "https://metadesign.com/en/work/airtel",
  "category": "Telecommunications",
  "description": "Airtel's brand colors are a bold red (#D40000), complemented by shades of blue-gray (#374150), black (#000000), dark gray (#2D2D2D), and light gray (#DCDCDC). These colors are known from the company's official website and MetaDesign's work portfolio."
}