{
  "title": "Associated Press",
  "colors": [
    "FF322E"
  ],
  "brandUrl": "http://www.ap.org/",
  "sourceUrl": "https://www.ap.org/wp-content/uploads/2024/02/ap_brand-assets.zip",
  "category": "News and Journalism",
  "description": "The Associated Press (AP) is renowned for its signature vibrant crimson red color, represented by the hexadecimal code #FF322E. Known for its reliability and professionalism in delivering news, AP's branding draws attention with this bold hue. The color is consistently featured in their branding materials that are accessible through the AP's official brand assets."
}