{
  "title": "Daimler AG",
  "colors": [
    "E6E6E6"
  ],
  "brandUrl": "http://daimler.com",
  "sourceUrl": "https://designnavigator.daimler.com/Daimler_Color_System?lang=en#color-codes",
  "category": "Automotive",
  "description": "Daimler AG is recognized for its use of the color E6E6E6, a sleek, neutral tone that reflects its commitment to sophistication and innovation. The brand's distinctive color scheme is documented on their official design resource, the Daimler Color System, which provides detailed guidance on their visual identity."
}