{
  "title": "Deezer",
  "colors": [
    "FF0000",
    "FFED00",
    "FF0092",
    "C2FF00",
    "00C7F2",
    "C1F1FC",
    "EBFFAC",
    "FFC2E5",
    "FFAAAA"
  ],
  "brandUrl": "http://www.deezer.com/",
  "sourceUrl": "http://www.deezer.com/us/company/press",
  "category": "Music Streaming",
  "description": "Deezer's vibrant color palette uses a range of striking and dynamic colors such as bold red (FF0000), bright yellow (FFED00), and electric pink (FF0092) to capture attention. The colors are known from the brand's presence on platforms such as their official website and press releases."
}