{
  "title": "Massachusetts Institute of Technology",
  "colors": [
    "A31F34",
    "8A8B8C",
    "C2C0BF"
  ],
  "brandUrl": "http://web.mit.edu/",
  "sourceUrl": "http://web.mit.edu/graphicidentity/colors.html",
  "category": "Education",
  "description": "The brand colors of the Massachusetts Institute of Technology (MIT) include A31F34, an MIT red that symbolizes energy and innovation; 8A8B8C, a neutral gray representing balance and neutrality; and C2C0BF, a light gray for accessibility and inclusion. These colors are formally documented and can be referenced at http://web.mit.edu/graphicidentity/colors.html."
}