{
  "title": "MGM Resorts International",
  "colors": [
    "996D15",
    "FFFFFF",
    "161616"
  ],
  "brandUrl": "https://www.mgmresorts.com/en.html",
  "sourceUrl": "https://brandfetch.com/mgmresorts.com",
  "category": "Hospitality and Entertainment",
  "description": "MGM Resorts International is recognized for its rich color palette combining a luxurious gold (#996D15), a crisp white (#FFFFFF), and a sleek black (#161616). These colors are sourced from its brand's official presence on platforms such as their brand website and third-party brand repository, Brandfetch."
}