{
  "title": "Microsoft",
  "colors": [
    "FFF100",
    "FF8C00",
    "E81123",
    "EC008C",
    "68217A",
    "00188F",
    "00BCF2",
    "00B294",
    "009E49",
    "BAD80A"
  ],
  "brandUrl": "https://www.microsoft.com/en-us/",
  "sourceUrl": "https://ratnacahayarina.files.wordpress.com/2014/03/microsoft.pdf",
  "category": "Technology",
  "description": "Microsoft is a leading technology company known for its vibrant and diverse brand colors, including shades of yellow, orange, red, pink, purple, blue, and green. These colors have been officially captured and referenced from a document provided by Microsoft: https://ratnacahayarina.files.wordpress.com/2014/03/microsoft.pdf"
}