{
  "title": "Northwestern University",
  "colors": [
    "4E2A84",
    "836EAA",
    "401F68",
    "B6ACD1",
    "E4E0EE",
    "342F2E",
    "716C6B",
    "BBB8B8",
    "D8D6D6"
  ],
  "brandUrl": "http://www.northwestern.edu",
  "sourceUrl": "https://www.northwestern.edu/brand/visual-identity/color-palettes/",
  "category": "Higher Education",
  "description": "The official color palette of Northwestern University features a rich blend of purples, grays, and neutrals, reflecting both the institution's historical and academic identity. These colors are sourced directly from the university's visual identity guidelines, ensuring consistency and recognition across all visual communications."
}