{
  "title": "Petrobras",
  "colors": [
    "FFC632",
    "007F3F"
  ],
  "brandUrl": "http://petrobras.com",
  "sourceUrl": null,
  "category": "Energy",
  "description": "Petrobras' brand colors, characterized by a vibrant yellow (#FFC632) and a deep green (#007F3F), are widely recognized in the energy industry for their visual resemblance to the dynamic and sustainable aspects of their operations. These colors are sourced from their official brand materials, as seen on their website and other promotional content."
}