{
  "title": "Wooga",
  "colors": [
    "5B009C"
  ],
  "brandUrl": "https://www.wooga.com/",
  "sourceUrl": null,
  "category": "Mobile Gaming",
  "description": "The brand Wooga is associated with a vibrant and bold color scheme, primarily featuring the hue #5B009C. This distinct purple shade aligns with their playful and creative image in the gaming industry. Information about Wooga's brand colors is gathered from its public branding materials and online presence, establishing a cohesive and recognizable visual identity."
}